Workbook

Sheet Test Cases
A1: Test Case ID | B1: Category | C1: Test Case | D1: Expected Result | E1: Actual Result | F1: Test Result | G1: Test Result Criteria | H1: Requirement Traceability | I1: Rubric Mapping | J1: Test Result Reasoning
A2: TC-001 | B2: Individual-paper retrieval | C2: What is the main idea of the sketching approach to program synthesis? | D2: Answer explains sketching as a partial-program technique: the programmer writes a sketch with holes/unknowns, and a solver fills them. Draws on aplas_Solar-Lezama09 and/or pldi_Solar-LezamaRBE05. Sources line names one or both of these papers. | E2: Assistant The main idea of the sketching approach to program synthesis is to allow programmers to express their high-level insights about a problem by writing a sketch, which is a partial program that encodes the structure of a solution while leaving its low-level details unspecified. The programmer provides either a reference implementation or a set of test routines that the synthesized code must pass. The synthesis engine then derives the missing details in the sketch to produce a working implementation that satisfies the correctness criteria established by the programmer. This approach combines the programmer's insights with the synthesizer's ability to reason about low-level details, enabling the implementation of complex algorithms. As stated in the paper, "the synthesizer’s ability to reason exhaustively about all the low-level details of the problem" is a key aspect of this method (The Sketching Approach to Program Synthesis (2009)). Sources Sources: The Sketching Approach to Program Synthesis (2009); Synthesis of Recursive ADT Transformations from Reusable Templates (2015); Learning to Infer Program Sketches (2019); Unsupervised Learning by Program Synthesis (2015); JSKETCH: Sketching for Java (2015) Quotation support: 1/1 passages verified. [response time 14.6s] [usage path=direct tokens=2272 calls=1] | F2: Pass | G2: Pass: answer mentions a hole/unknown/template concept and names a real sketching paper in Sources. Fail: answer is generic, names no source, or cites an unrelated paper. | H2: Spec S4/S6.1 - individual-paper retrieval; Design S4-5 - retrieval and citation | I2: Primary: P5 Retrieval approach. Supporting: P4 System behavior; P6 Workflow; P7 Evaluation evidence. | J2: Explains a sketch as a partial program with unspecified low-level details filled in by a synthesizer; Sources names The Sketching Approach to Program Synthesis (2009) first. Three of the five listed sources are unrelated (Learning to Infer Program Sketches, etc.), which does not affect the pass.
A3: TC-002 | B3: Individual-paper retrieval | C3: What does the CRUXEval benchmark measure? | D3: Answer states CRUXEval evaluates code reasoning via input/output prediction and execution, citing icml_GuRLSS024. | E3: Assistant The CRUXEval benchmark measures code reasoning, understanding, and execution through two main tasks: output prediction (CRUXEVAL-O) and input prediction (CRUXEVAL-I). It consists of 800 Python functions, each paired with input-output examples. The benchmark evaluates the abilities of code language models (LMs) to reason about the execution behavior of simple Python programs. Specifically, it aims to assess how well models can predict outputs given inputs and vice versa. As stated in the documents, "CRUXEVAL examines the abilities of code LMs to reason about the execution behaviour of simple Python programs." (CRUXEval: A Benchmark for Code Reasoning, Understanding and Execution (2024)) Sources Sources: CRUXEval: A Benchmark for Code Reasoning, Understanding and Execution (2024) Quotation support: 1/1 passages verified. [response time 2.5s] [usage path=direct tokens=2556 calls=1] | F3: Pass | G3: Pass: answer mentions input/output prediction or execution, and Sources line names the CRUXEval paper. Fail: benchmark purpose is wrong or unsourced. | H3: Spec S6.1 - individual-paper retrieval | I3: Primary: P5 Retrieval approach. Supporting: P4 System behavior; P7 Evaluation evidence. | J3: States two tasks, output prediction and input prediction, on 800 Python functions; Sources names the CRUXEval paper only.
A4: TC-003 | B4: Individual-paper retrieval | C4: What does the LINC paper do with logical reasoning? | D4: Answer describes LINC's neurosymbolic approach combining an LLM with a symbolic first-order logic theorem prover, citing emnlp_OlaussonGLZSTL23. | E4: Assistant The LINC paper presents a neurosymbolic approach to logical reasoning, which it refers to as "Logical Inference via Neurosymbolic Computation." In this approach, the language model acts as a semantic parser that translates natural language premises and conclusions into first-order logic (FOL) expressions. These expressions are then processed by an external theorem prover that performs deductive inference to determine the truth value of the conclusion based on the formalized premises. The process is modular and consists of two main steps: first, converting natural language to FOL, and second, using a symbolic FOL theorem prover to derive conclusions. Additionally, a third majority voting step is incorporated to enhance performance. The paper reports significant performance improvements on various datasets compared to baseline strategies (LINC: A Neurosymbolic Approach for Logical Reasoning by Combining Language Models with First-Order Logic Provers (2023))(LINC: A Neurosymbolic Approach for Logical Reasoning by Combining Language Models with First-Order Logic Provers (2023)). Sources Sources: LINC: A Neurosymbolic Approach for Logical Reasoning by Combining Language Models with First-Order Logic Provers (2023); Position: Future Research and Challenges Remain Towards AI for Software Engineering (2025); Program Synthesis from Polymorphic Reﬁnement Types (2016) Quotation support: 1/1 passages verified. [response time 2.5s] [usage path=direct tokens=2408 calls=1] | F4: Pass | G4: Pass: answer mentions first-order logic or a theorem prover (for example Prover9) AND the Sources line names the LINC paper (emnlp_OlaussonGLZSTL23). Fail: LINC is described only as 'neurosymbolic' or 'scalable logical reasoning' with no mechanism, which is the run-1 failure. | H4: Spec S6.1 - individual-paper retrieval | I4: Primary: P5 Retrieval approach. Supporting: P7 Evaluation evidence. | J4: Names first-order logic and an external theorem prover; Sources names the LINC paper first. Two unrelated sources are also listed.
A5: TC-004 | B5: Individual-paper retrieval | C5: What is adaptive concretization? | D5: Answer explains it as a technique for parallel program synthesis that concretizes parts of the search space (e.g. via parallel/randomized SAT solving), citing cav_JeonQSF15. | E5: Assistant Adaptive concretization is a program synthesis technique that enhances the efficiency of parallel program synthesis by dynamically identifying which unknowns in a synthesis problem are best suited for explicit search versus symbolic search. The main idea is to partially concretize a randomly chosen, likely influential subset of the unknowns and to parallelize the explicit search on those unknowns where that search style is more suitable. This method combines the strengths of both symbolic search, which reduces synthesis to a formula for a SAT solver, and explicit search, which employs brute force or random search to find solutions. As described in the documents, "the key observation behind adaptive concretization is that in a challenging synthesis problem, there are some unknowns that are best suited for explicit search and some that are best suited for symbolic search through constraint solving" (An empirical study of adaptive concretization for parallel program synthesis (2017)). The technique has shown to be effective and scalable in various benchmarks, outperforming traditional methods in many cases (Adaptive Concretization for Parallel Program Synthesis (2015)). Sources Sources: An empirical study of adaptive concretization for parallel program synthesis (2017); Adaptive Concretization for Parallel Program Synthesis (2015) Quotation support: 1/1 passages verified. [response time 2.5s] [usage path=direct tokens=2241 calls=1] | F5: Pass | G5: Pass: answer mentions concretization and parallel/SAT-based search, cites the right paper. Fail: confuses this with a different synthesis technique. | H5: Spec S6.1 - individual-paper retrieval | I5: Primary: P5 Retrieval approach. Supporting: P7 Evaluation evidence. | J5: Explains partial concretization of unknowns with parallel explicit and SAT-based symbolic search; Sources includes Adaptive Concretization for Parallel Program Synthesis (2015).
A6: TC-005 | B6: Individual-paper retrieval | C6: What is the Euler system for? | D6: Answer identifies Euler as a system for numerical optimization of programs, citing cav_ChaudhuriS12. | E6: Assistant The Euler system is designed for solving difficult optimization problems involving programs. Specifically, it aims to find an input \( x \) to a function \( P \) (written in a standard C-like language) such that the output \( P(x) \) is minimized with respect to an appropriate distance measure on the space of outputs of \( P \). The paper states, "Euler, a system for solving unconstrained optimization problems" and emphasizes that many problems in software engineering can be framed as such optimization questions (Euler: A System for Numerical Optimization of Programs⋆ (2012)). Sources Sources: Euler: A System for Numerical Optimization of Programs⋆ (2012); A Language for Counterfactual Generative Models (2021) Quotation support: 1/1 passages verified. [response time 1.5s] [usage path=direct tokens=2343 calls=1] | F6: Pass | G6: Pass: answer mentions numerical optimization and cites Euler's paper. Fail: wrong system purpose or no citation. | H6: Spec S6.1 - individual-paper retrieval | I6: Primary: P5 Retrieval approach. Supporting: P7 Evaluation evidence. | J6: Describes Euler as a system for optimizing programs, quoting the paper; the paper title 'A System for Numerical Optimization of Programs' is in the citation and Sources. One unrelated source also listed.
A7: TC-006 | B7: Individual-paper retrieval | C7: What does the self-repair paper conclude about fixing code generation errors? | D7: Answer summarizes the finding that self-repair gives inconsistent gains and is not a reliable fix across models, citing iclr_OlaussonIW0S24 ("Is Self-Repair a Silver Bullet for Code Generation?"). | E7: Assistant The paper "Is Self-Repair A Silver Bullet For Code Generation?" concludes that while self-repair, where the model debugs and repairs its own code, has become a popular method to enhance performance in code generation, its efficacy remains poorly understood in many settings. The authors found that "when the cost of carrying out repair is taken into account, performance gains are often modest." They suggest that the performance gains from self-repair do not always correlate perfectly with baseline performance, which may be influenced by factors such as the difficulty of the initial programs generated, the ambiguity in natural language specifications, and the informativeness of unit tests (Is Self-Repair A Silver Bullet For Code Generation? (2024)). Sources Sources: Is Self-Repair A Silver Bullet For Code Generation? (2024); LiveCodeBench: Holistic and Contamination Free Evaluation of Large Language Models for Code (2024) Quotation support: 1/1 passages verified. [response time 2.3s] [usage path=direct tokens=2421 calls=1] | F7: Pass | G7: Pass: answer reflects a qualified/skeptical conclusion, not a blanket "self-repair works" claim, and cites the right paper. Fail: overstates self-repair's effectiveness or misattributes the source. | H7: Spec S6.1/S6.6 - retrieval with accurate conclusion, not overclaiming | I7: Primary: P4 System behavior. Supporting: P7 Evaluation evidence; P5 Retrieval approach. | J7: Reports a qualified conclusion ('performance gains are often modest') and cites the Self-Repair paper first in Sources.
A8: TC-007 | B8: Individual-paper retrieval | C8: How do verifiers act as oracles in CEGIS? | D8: Answer explains the counterexample-guided loop: a verifier checks a candidate program and returns a counterexample when it fails, which drives the next synthesis attempt. The question is not blocked or altered. | E8: Assistant In the context of CEGIS (Counterexample-Guided Inductive Synthesis), verifiers act as oracles by checking the validity of candidate programs and providing counterexamples when those candidates do not satisfy the required specifications. The passage states, "The checker takes in this candidate program s and produces an adversarial counter example ce ∈D \D′ which invalidates s." This indicates that the verifier (or checker) evaluates the candidate and, if it finds that the candidate does not meet the specifications, it generates a counterexample to guide the synthesis process. Thus, the verifier serves the role of an oracle by offering critical feedback that helps refine the synthesis of the program. This mechanism is described in the paper as follows: "CEGIS is composed of two adversarial sub-routines, a synthesizer and a checker." The checker, in this case, acts as the oracle that provides necessary information to improve the candidate program. Sources Sources: MIMEQA: Towards Socially-Intelligent Nonverbal Foundation Models (2025); CAV 2021 proceedings volume; Selecting Representative Examples for Program Synthesis (2017) Quotation support: 2/2 passages verified. [response time 3.8s] [usage path=direct tokens=2398 calls=1] | F8: Pass | G8: Pass: answer describes the verify / counterexample loop and is not a refusal. Fail: the answer says the documents do not contain the information (the run-1 failure), or the question is blocked or visibly altered. The sanitizer false-positive aspect is isolated in TC-042 so this case measures retrieval only. | H8: Spec 6.1; Architecture 10 (retrieval relevance); Design 4-5 | I8: Primary: P9a Trade-offs: retrieval strategies. Supporting: P5 Retrieval approach; P7 Evaluation evidence. | J8: Describes the checker returning an adversarial counterexample that drives the next candidate; not a refusal and the question was not altered. Quotes verified 2/2. Sources line lists MIMEQA (2025) first, which is not a CEGIS paper; the label list is noisy but the answer is grounded.
A9: TC-008 | B9: Individual-paper retrieval | C9: What year was the sketching paper by Solar-Lezama and Bodik published, and what conference? | D9: Answer names PLDI 2005 for "Programming by Sketching for Bit-Streaming Programs" (pldi_Solar-LezamaRBE05), consistent with the resolved year metadata. | E9: Assistant Programming by Sketching for Bit-Streaming Programs was published in 2005 at PLDI. Sources Sources: Programming by Sketching for Bit-Streaming Programs (2005) Quotation support: 0/0 passages verified. [response time 0.2s] [usage path=metadata tokens=0 calls=0] | F9: Pass | G9: Pass: year and venue are correct and match the resolved year field, not a guessed or hallucinated date. Fail: wrong year/venue or a date not grounded in the corpus. | H9: Design S4 - publication-year resolution | I9: Primary: P4 System behavior. Supporting: P5 Retrieval approach. | J9: Answers PLDI 2005 via the metadata path (0 tokens, 0 calls), matching the resolved year field.
A10: TC-009 | B10: Individual-paper retrieval | C10: What does this collection say about AlphaFold and protein structure prediction? | D10: The collection has no content on AlphaFold or protein folding (0 mentions of either across all 153 documents). The answer says so plainly instead of inventing content. If the Sources line lists anything, the answer must not claim those papers discuss protein structure. | E10: Assistant The documents do not cover AlphaFold or protein structure prediction. Sources Sources (retrieved, not used): Improved modeling of RNA‑binding protein motifs in an interpretable neural model of RNA splicing (2024); CRUXEval: A Benchmark for Code Reasoning, Understanding and Execution (2024); PPSN 2014 proceedings volume; Lynx: A Programmatic SAT Solver for the RNA-Folding Problem (2012); CAV 2021 proceedings volume; Is Self-Repair A Silver Bullet For Code Generation? (2024); MIMEQA: Towards Socially-Intelligent Nonverbal Foundation Models (2025); ENCOMPASS: Enhancing Agent Programming with Search Over Program Execution Paths (2025); Using Program Synthesis for Social Recommendations (2012); Synthesizing Data-structure Manipulations from Storyboards (2011); Sparling: End-To-End Spatial Concept Learning Via Extremely Sparse Activations (2023); Delta-Decision Procedures for Exists-Forall Problems over the Reals (2018); Sampling for Bayesian Program Learning (2016); Liquid Information Flow Control (2020); Fusion 360 Gallery: A Dataset and Environment for Programmatic CAD Construction from Human Design Sequences (2021) Quotation support: 0/0 passages verified. [response time 6.6s] [usage path=agent tokens=17475 calls=4] | F10: Pass | G10: Pass: answer states the collection does not cover this, with no invented AlphaFold or protein-folding claims. Fail: the answer describes protein-structure content, or cites a paper as if it supported such content. (v1 asked about quantum computing; a corpus scan showed the collection does contain quantum content, so that oracle was wrong. The quantum question is now a positive control in TC-075.) | H10: Spec 1 and 6.6 (honest non-answer); Test Strategy 8.1 bullet 3 | I10: Primary: P4 System behavior. Supporting: P10 Remaining limitations; P7 Evaluation evidence. | J10: States the collection does not cover AlphaFold or protein structure and invents nothing. The Sources line is labelled 'retrieved, not used' and lists many unrelated papers, so no paper is presented as supporting protein-structure content. The list is long (15 entries) but correctly marked.
A11: TC-010 | B11: Individual-paper retrieval | C11: What is the main idea of the main idea of the approach the approach uses? | D11: A deliberately malformed/repetitive question. Answer either asks for clarification or makes a reasonable best-effort attempt without crashing or returning an empty response. | E11: Assistant The main idea of the approach described in the document is to use a metric-based synthesis algorithm that relaxes the observational equivalence criterion into observational similarity by employing a distance metric. This method constructs an approximate version space by clustering together values that are similar, which helps to reduce the search space that the synthesizer needs to explore. The paper states, "the key idea behind metric-based synthesis is to relax the observational equivalence criterion into observational similarity by using a distance metric" (Metric Program Synthesis (2022)). Sources Sources: Metric Program Synthesis (2022); MathDSL: A Domain-Specific Language for Concise Mathematical Solutions Via Program Synthesis (2024); CAV 2019 proceedings volume; Synthesizing Data-structure Manipulations from Storyboards (2011); Program Synthesis Guided Reinforcement Learning for Partially Observed Environments (2021) Quotation support: 1/1 passages verified. [response time 2.3s] [usage path=direct tokens=2248 calls=1] | F11: Pass | G11: Pass: system returns a coherent response or a clarification request, no exception/crash. Fail: unhandled error, blank output, or a stack trace surfaces to the user. | H11: Design S10 - error handling for malformed input | I11: Primary: P4 System behavior. Supporting: P9e Trade-offs: operational considerations. | J11: Best-effort answer on metric program synthesis, no crash and no empty output; quote verified 1/1. It did not ask for clarification but the criteria accept a coherent response.
A12: TC-011 | B12: Cross-paper comparison | C12: Compare LiveCodeBench and CRUXEval: how do they differ in what they test? | D12: Answer addresses each benchmark separately (LiveCodeBench: holistic, contamination-free code evaluation; CRUXEval: input/output prediction and execution reasoning) then states the difference, citing both iclr_JainHGLYZWSSS25 and icml_GuRLSS024. | E12: Assistant LiveCodeBench and CRUXEval differ in their focus and the specific aspects of code-related capabilities they evaluate. **LiveCodeBench**: - Focuses on a comprehensive and contamination-free evaluation of large language models (LLMs) for code. - It collects problems from three competition platforms: LeetCode, AtCoder, and CodeForces. - Evaluates a broader range of code-related capabilities, including "self-repair, code execution, and test output prediction, beyond just code generation." - Hosts over five hundred coding problems published between May 2023 and May 2024 and has evaluated 18 base LLMs and 34 instruction-tuned LLMs. - The study presents findings on contamination, holistic performance comparisons, and potential overfitting in existing benchmarks (LiveCodeBench: Holistic and Contamination Free Evaluation of Large Language Models for Code (2024)). **CRUXEval**: - Specifically designed to evaluate code reasoning, understanding, and execution. - Introduces two tasks: output prediction (CRUXEVAL-O) to measure code execution and input prediction (CRUXEVAL-I) to assess code reasoning and understanding. - The benchmark examines the abilities of code LMs to reason about the execution behavior of simple Python programs, ensuring that the samples are solvable by a university-level CS graduate. - It highlights the performance of models on these tasks, noting that even the best models struggle with execution prediction and code reasoning despite high training data volumes (CRUXEval: A Benchmark for Code Reasoning, Understanding and Execution (2024)). **Comparison**: - **Scope**: LiveCodeBench has a broader scope, evaluating various capabilities beyond just reasoning and execution, while CRUXEval is focused specifically on reasoning and execution tasks. - **Problem Sources**: LiveCodeBench uses problems from competitive programming platforms, whereas CRUXEval uses simpler, controlled samples designed for evaluating specific reasoning and execution abilities. - **Model Evaluation**: LiveCodeBench evaluates a larger number of models (over 50), while CRUXEval discusses performance metrics for fewer models, emphasizing the challenges they face in reasoning and execution tasks. In summary, LiveCodeBench provides a holistic evaluation of LLMs across various coding capabilities, while CRUXEval zeroes in on the reasoning and execution aspects of code understanding. Sources Sources: LiveCodeBench: Holistic and Contamination Free Evaluation of Large Language Models for Code (2024); CRUXEval: A Benchmark for Code Reasoning, Understanding and Execution (2024) Quotation support: 1/1 passages verified. [response time 6.5s] [usage path=agent tokens=3437 calls=2] | F12: Pass | G12: Pass: both papers appear in Sources, answer is structured per-paper rather than blended, and the stated difference is accurate. Fail: only one paper is used, or the answer blends both into an undifferentiated summary. | H12: Spec S6.2/S6.5 - cross-paper comparison, structured answers; Design S6 - comparison addendum | I12: Primary: P4 System behavior. Supporting: P5 Retrieval approach; P7 Evaluation evidence. | J12: Per-paper bullets for LiveCodeBench (holistic, contamination-free, self-repair, execution, test output prediction) and CRUXEval (input and output prediction, execution reasoning), then the difference; both papers are in Sources.
... A146: TC-145 | B146: Trend / change over time | C146: How did program synthesis research change from 2005 to 2020? | D146: Treated as a change-over-time question: the answer is ordered oldest first, each period cites a paper that was retrieved, every year given belongs to the cited paper, and thin coverage is stated when it applies. | E146: Assistant The documents do not cover the changes in program synthesis research from 2005 to 2020. Sources Sources (retrieved, not used): Synthesis of Recursive ADT Transformations from Reusable Templates (2015); Learning to Infer Program Sketches (2019); Synthesizing Data-structure Manipulations from Storyboards (2011); Top-Down Synthesis for Library Learning (2023); Bridging the Gap Between General-Purpose and Domain-Speciﬁc Compilers with Synthesis (2015); Neurosymbolic World Models for Sequential Decision Making (2025) Quotation support: 0/0 passages verified. [response time 1.8s] [usage path=direct tokens=2442 calls=1] | F146: Fail | G146: Pass: chronological order, each bullet cited and dated by the cited paper, no invented period. Fail: a single-paper answer that ignores the range, a timeline with an uncited period, or years that do not match the cited papers. | H146: Spec 6.3; code review run 3 finding on trend wording (TC-136) | I146: Primary: P4 System behavior. Supporting: P6 Workflow; P5 Retrieval approach. | J146: The question is not recognised as a change-over-time question (see TC-136: 'change' is missing from _TREND_RE), so it took the direct single-call path and returned 'The documents do not cover the changes in program synthesis research from 2005 to 2020.' with six retrieved papers (2011 to 2025) listed as 'retrieved, not used'. There is no chronological timeline, no thin-coverage statement and the range 2005 to 2020 was ignored.

Sheet Summary
A1: Test run summary
A3: Result | B3: Count
A4: Pass | B4: =COUNTIF('Test Cases'!$F$2:$F$146,"Pass") -> 137
A5: Fail | B5: =COUNTIF('Test Cases'!$F$2:$F$146,"Fail") -> 7
A6: Blocked | B6: =COUNTIF('Test Cases'!$F$2:$F$146,"Blocked") -> 1
A7: Accepted limitation | B7: =COUNTIF('Test Cases'!$F$2:$F$146,"Accepted limitation") -> 0
A8: Not Run | B8: =COUNTIF('Test Cases'!$F$2:$F$146,"Not Run")+COUNTBLANK('Test Cases'!$F$2:$F$146) -> 0
A9: Total cases | B9: =SUM(B4:B8) -> 145
A10: Pass rate of cases run | B10: =IF(B9-B8=0,"",B4/(B9-B8)) -> 0.94482759
A12: Category | B12: Cases | C12: Pass | D12: Fail | E12: Blocked | F12: Accepted limitation | G12: Not Run
A13: Individual-paper retrieval | B13: =COUNTIF('Test Cases'!$B$2:$B$146,A13) -> 20 | C13: =COUNTIFS('Test Cases'!$B$2:$B$146,$A13,'Test Cases'!$F$2:$F$146,"Pass") -> 20 | D13: =COUNTIFS('Test Cases'!$B$2:$B$146,$A13,'Test Cases'!$F$2:$F$146,"Fail") -> 0 | E13: =COUNTIFS('Test Cases'!$B$2:$B$146,$A13,'Test Cases'!$F$2:$F$146,"Blocked") -> 0 | F13: =COUNTIFS('Test Cases'!$B$2:$B$146,$A13,'Test Cases'!$F$2:$F$146,"Accepted limitation") -> 0 | G13: =B13-C13-D13-E13-F13 -> 0
A14: Cross-paper comparison | B14: =COUNTIF('Test Cases'!$B$2:$B$146,A14) -> 12 | C14: =COUNTIFS('Test Cases'!$B$2:$B$146,$A14,'Test Cases'!$F$2:$F$146,"Pass") -> 11 | D14: =COUNTIFS('Test Cases'!$B$2:$B$146,$A14,'Test Cases'!$F$2:$F$146,"Fail") -> 1 | E14: =COUNTIFS('Test Cases'!$B$2:$B$146,$A14,'Test Cases'!$F$2:$F$146,"Blocked") -> 0 | F14: =COUNTIFS('Test Cases'!$B$2:$B$146,$A14,'Test Cases'!$F$2:$F$146,"Accepted limitation") -> 0 | G14: =B14-C14-D14-E14-F14 -> 0
A15: Trend / change over time | B15: =COUNTIF('Test Cases'!$B$2:$B$146,A15) -> 17 | C15: =COUNTIFS('Test Cases'!$B$2:$B$146,$A15,'Test Cases'!$F$2:$F$146,"Pass") -> 13 | D15: =COUNTIFS('Test Cases'!$B$2:$B$146,$A15,'Test Cases'!$F$2:$F$146,"Fail") -> 4 | E15: =COUNTIFS('Test Cases'!$B$2:$B$146,$A15,'Test Cases'!$F$2:$F$146,"Blocked") -> 0 | F15: =COUNTIFS('Test Cases'!$B$2:$B$146,$A15,'Test Cases'!$F$2:$F$146,"Accepted limitation") -> 0 | G15: =B15-C15-D15-E15-F15 -> 0
A16: Grounding and citation | B16: =COUNTIF('Test Cases'!$B$2:$B$146,A16) -> 15 | C16: =COUNTIFS('Test Cases'!$B$2:$B$146,$A16,'Test Cases'!$F$2:$F$146,"Pass") -> 15 | D16: =COUNTIFS('Test Cases'!$B$2:$B$146,$A16,'Test Cases'!$F$2:$F$146,"Fail") -> 0 | E16: =COUNTIFS('Test Cases'!$B$2:$B$146,$A16,'Test Cases'!$F$2:$F$146,"Blocked") -> 0 | F16: =COUNTIFS('Test Cases'!$B$2:$B$146,$A16,'Test Cases'!$F$2:$F$146,"Accepted limitation") -> 0 | G16: =B16-C16-D16-E16-F16 -> 0
A17: Security and adversarial | B17: =COUNTIF('Test Cases'!$B$2:$B$146,A17) -> 16 | C17: =COUNTIFS('Test Cases'!$B$2:$B$146,$A17,'Test Cases'!$F$2:$F$146,"Pass") -> 16 | D17: =COUNTIFS('Test Cases'!$B$2:$B$146,$A17,'Test Cases'!$F$2:$F$146,"Fail") -> 0 | E17: =COUNTIFS('Test Cases'!$B$2:$B$146,$A17,'Test Cases'!$F$2:$F$146,"Blocked") -> 0 | F17: =COUNTIFS('Test Cases'!$B$2:$B$146,$A17,'Test Cases'!$F$2:$F$146,"Accepted limitation") -> 0 | G17: =B17-C17-D17-E17-F17 -> 0
A18: Performance and cost | B18: =COUNTIF('Test Cases'!$B$2:$B$146,A18) -> 12 | C18: =COUNTIFS('Test Cases'!$B$2:$B$146,$A18,'Test Cases'!$F$2:$F$146,"Pass") -> 11 | D18: =COUNTIFS('Test Cases'!$B$2:$B$146,$A18,'Test Cases'!$F$2:$F$146,"Fail") -> 1 | E18: =COUNTIFS('Test Cases'!$B$2:$B$146,$A18,'Test Cases'!$F$2:$F$146,"Blocked") -> 0 | F18: =COUNTIFS('Test Cases'!$B$2:$B$146,$A18,'Test Cases'!$F$2:$F$146,"Accepted limitation") -> 0 | G18: =B18-C18-D18-E18-F18 -> 0
A19: Data quality and corpus integrity | B19: =COUNTIF('Test Cases'!$B$2:$B$146,A19) -> 13 | C19: =COUNTIFS('Test Cases'!$B$2:$B$146,$A19,'Test Cases'!$F$2:$F$146,"Pass") -> 13 | D19: =COUNTIFS('Test Cases'!$B$2:$B$146,$A19,'Test Cases'!$F$2:$F$146,"Fail") -> 0 | E19: =COUNTIFS('Test Cases'!$B$2:$B$146,$A19,'Test Cases'!$F$2:$F$146,"Blocked") -> 0 | F19: =COUNTIFS('Test Cases'!$B$2:$B$146,$A19,'Test Cases'!$F$2:$F$146,"Accepted limitation") -> 0 | G19: =B19-C19-D19-E19-F19 -> 0
A20: Conversational usability | B20: =COUNTIF('Test Cases'!$B$2:$B$146,A20) -> 14 | C20: =COUNTIFS('Test Cases'!$B$2:$B$146,$A20,'Test Cases'!$F$2:$F$146,"Pass") -> 13 | D20: =COUNTIFS('Test Cases'!$B$2:$B$146,$A20,'Test Cases'!$F$2:$F$146,"Fail") -> 1 | E20: =COUNTIFS('Test Cases'!$B$2:$B$146,$A20,'Test Cases'!$F$2:$F$146,"Blocked") -> 0 | F20: =COUNTIFS('Test Cases'!$B$2:$B$146,$A20,'Test Cases'!$F$2:$F$146,"Accepted limitation") -> 0 | G20: =B20-C20-D20-E20-F20 -> 0
A21: Regression and acceptance | B21: =COUNTIF('Test Cases'!$B$2:$B$146,A21) -> 7 | C21: =COUNTIFS('Test Cases'!$B$2:$B$146,$A21,'Test Cases'!$F$2:$F$146,"Pass") -> 7 | D21: =COUNTIFS('Test Cases'!$B$2:$B$146,$A21,'Test Cases'!$F$2:$F$146,"Fail") -> 0 | E21: =COUNTIFS('Test Cases'!$B$2:$B$146,$A21,'Test Cases'!$F$2:$F$146,"Blocked") -> 0 | F21: =COUNTIFS('Test Cases'!$B$2:$B$146,$A21,'Test Cases'!$F$2:$F$146,"Accepted limitation") -> 0 | G21: =B21-C21-D21-E21-F21 -> 0
A22: Architecture and workflow verification | B22: =COUNTIF('Test Cases'!$B$2:$B$146,A22) -> 9 | C22: =COUNTIFS('Test Cases'!$B$2:$B$146,$A22,'Test Cases'!$F$2:$F$146,"Pass") -> 9 | D22: =COUNTIFS('Test Cases'!$B$2:$B$146,$A22,'Test Cases'!$F$2:$F$146,"Fail") -> 0 | E22: =COUNTIFS('Test Cases'!$B$2:$B$146,$A22,'Test Cases'!$F$2:$F$146,"Blocked") -> 0 | F22: =COUNTIFS('Test Cases'!$B$2:$B$146,$A22,'Test Cases'!$F$2:$F$146,"Accepted limitation") -> 0 | G22: =B22-C22-D22-E22-F22 -> 0
A23: Operational and configuration | B23: =COUNTIF('Test Cases'!$B$2:$B$146,A23) -> 10 | C23: =COUNTIFS('Test Cases'!$B$2:$B$146,$A23,'Test Cases'!$F$2:$F$146,"Pass") -> 9 | D23: =COUNTIFS('Test Cases'!$B$2:$B$146,$A23,'Test Cases'!$F$2:$F$146,"Fail") -> 0 | E23: =COUNTIFS('Test Cases'!$B$2:$B$146,$A23,'Test Cases'!$F$2:$F$146,"Blocked") -> 1 | F23: =COUNTIFS('Test Cases'!$B$2:$B$146,$A23,'Test Cases'!$F$2:$F$146,"Accepted limitation") -> 0 | G23: =B23-C23-D23-E23-F23 -> 0
A24: Total | B24: =SUM(B13:B23) -> 145 | C24: =SUM(C13:C23) -> 137 | D24: =SUM(D13:D23) -> 7 | E24: =SUM(E13:E23) -> 1 | F24: =SUM(F13:F23) -> 0 | G24: =SUM(G13:G23) -> 0
